rtl/peripherals/hex_decoder.v
module hex_decoder (
    input  wire [3:0] hex_digit,  
    output reg  [6:0] seg         
);
    always @(*) begin
        case (hex_digit)
            4'h0: seg = 7'b100_0000;
            4'h1: seg = 7'b111_1001; 
            4'h2: seg = 7'b010_0100; 
            4'h3: seg = 7'b011_0000; 
            4'h4: seg = 7'b001_1001; 
            4'h5: seg = 7'b001_0010; 
            4'h6: seg = 7'b000_0010; 
            4'h7: seg = 7'b111_1000; 
            4'h8: seg = 7'b000_0000; 
            4'h9: seg = 7'b001_0000; 
            4'hA: seg = 7'b000_1000; 
            4'hB: seg = 7'b000_0011; 
            4'hC: seg = 7'b100_0110; 
            4'hD: seg = 7'b010_0001; 
            4'hE: seg = 7'b000_0110; 
            4'hF: seg = 7'b000_1110; 
            default: seg = 7'b111_1111;
        endcase
    end
endmodule

rtl/memory/memory.v
module memory (
    input  wire        clk,
    input  wire        write_en,      
    input  wire [31:0] addr,          
    input  wire [31:0] write_data,    
    output wire [31:0] read_data      
);
    reg [31:0] ram [0:1023];        
    initial begin
        $readmemh("../firmware/program.hex", ram);
    end
    assign read_data = ram[addr[11:2]];
    always @(posedge clk) begin
        if (write_en) begin
            ram[addr[11:2]] <= write_data;
        end
    end

endmodule

rtl/core/alu.v
module alu (
    input  wire [31:0] a,
    input  wire [31:0] b,
    input  wire [3:0]  alu_ctrl,
    output reg  [31:0] result,
    output wire        zero
);

    assign zero = (result == 32'b0);

    always @(*) begin
        case (alu_ctrl)
            4'b0000: result = a + b;
            4'b0001: result = a - b;
            4'b0010: result = a & b;
            4'b0011: result = a | b;
            4'b0100: result = a ^ b;
            4'b0101: result = a << b[4:0];
            4'b0110: result = a >> b[4:0];
            4'b0111: result = $signed(a) >>> b[4:0];
            4'b1000: result = ($signed(a) < $signed(b)) ? 32'd1 : 32'd0;
            4'b1001: result = (a < b) ? 32'd1 : 32'd0;
            default: result = 32'b0;
        endcase
    end

endmodule

rtl/core/imm_gen.v
module imm_gen (
    input  wire [31:0] instr, 
    output reg  [31:0] imm    
);

    always @(*) begin
        case (instr[6:0])
            7'b0010011, 7'b0000011: begin
                imm = {{20{instr[31]}}, instr[31:20]};
            end
            7'b0100011: begin
                imm = {{20{instr[31]}}, instr[31:25], instr[11:7]};
            end
            7'b1100011: begin
                imm = {{19{instr[31]}}, instr[31], instr[7], instr[30:25], instr[11:8], 1'b0};
            end
            default: imm = 32'b0;
        endcase
    end
endmodule

rtl/core/reg_file.v
module reg_file (
    input  wire        clk,
    input  wire        rst,
    input  wire        reg_write,   
    input  wire [4:0]  rs1_addr,    
    input  wire [4:0]  rs2_addr,   
    input  wire [4:0]  rd_addr,     
    input  wire [31:0] write_data,  
    output wire [31:0] rs1_data,    
    output wire [31:0] rs2_data     
);


    reg [31:0] registers [31:0];
    integer i;
    assign rs1_data = (rs1_addr == 5'b0) ? 32'b0 : registers[rs1_addr];
    assign rs2_data = (rs2_addr == 5'b0) ? 32'b0 : registers[rs2_addr];

    always @(posedge clk or posedge rst) begin
        if (rst) begin
            for (i = 0; i < 32; i = i + 1) begin
                registers[i] <= 32'b0;
            end
        end else if (reg_write && (rd_addr != 5'b0)) begin
            registers[rd_addr] <= write_data;
        end
    end

endmodule

rtl/core/control_unit.v
module control_unit (
    input  wire [6:0] opcode,    
    input  wire [2:0] funct3,    
    input  wire [7:0] funct7,    
    output reg        reg_write,  
    output reg        alu_src,   
    output reg        mem_to_reg, 
    output reg        mem_write, 
    output reg        mem_read,  
    output reg        branch,     
    output reg  [3:0] alu_ctrl    
);

    always @(*) begin
        reg_write  = 1'b0;
        alu_src    = 1'b0;
        mem_to_reg = 1'b0;
        mem_write  = 1'b0;
        mem_read   = 1'b0;
        branch     = 1'b0;
        alu_ctrl   = 4'b0000;
        case (opcode)
            7'b0110011: begin
                reg_write = 1'b1;
                alu_src   = 1'b0;
                case (funct3)
                    3'b000: alu_ctrl = (funct7[5]) ? 4'b0001 : 4'b0000; 
                    3'b001: alu_ctrl = 4'b0101; 
                    3'b010: alu_ctrl = 4'b1000; 
                    3'b100: alu_ctrl = 4'b0100; 
                    3'b101: alu_ctrl = (funct7[5]) ? 4'b0111 : 4'b0110; 
                    3'b110: alu_ctrl = 4'b0011; 
                    3'b111: alu_ctrl = 4'b0010; 
                    default: alu_ctrl = 4'b0000;
                endcase
            end
            7'b0010011: begin
                reg_write = 1'b1;
                alu_src   = 1'b1;
                case (funct3)
                    3'b000: alu_ctrl = 4'b0000; 
                    3'b100: alu_ctrl = 4'b0100; 
                    3'b110: alu_ctrl = 4'b0011; 
                    3'b111: alu_ctrl = 4'b0010; 
                    default: alu_ctrl = 4'b0000;
                endcase
            end
            7'b0000011: begin
                reg_write  = 1'b1;
                alu_src    = 1'b1; 
                mem_to_reg = 1'b1;
                mem_read   = 1'b1;
                alu_ctrl   = 4'b0000;
            end
            7'b0100011: begin
                alu_src   = 1'b1;
                mem_write = 1'b1;
                alu_ctrl  = 4'b0000;
            end
            7'b1100011: begin
                branch   = 1'b1;
                alu_src  = 1'b0;
                alu_ctrl = 4'b0001;
            end

            default: ;
        endcase
    end

endmodule

rtl/core/pc.v
module pc (
    input  wire        clk,
    input  wire        rst,
    input  wire [31:0] next_pc, 
    output reg  [31:0] pc      
);

    always @(posedge clk or posedge rst) begin
        if (rst) begin
            pc <= 32'b0;      
        end else begin
            pc <= next_pc;   
        end
    end

endmodule

rtl/core/riscv_top.v
module riscv_top (
    input  wire        clk,
    input  wire        rst,
    output wire [31:0] pc_out,
    input  wire [31:0] instr,
    output wire [31:0] alu_result,
    output wire [31:0] mem_data_write,
    input  wire [31:0] mem_data_read,
    output wire        mem_read,
    output wire        mem_write
);
    wire [31:0] pc_current;
    wire [31:0] pc_next;
    wire [31:0] pc_plus_4;
    wire [31:0] pc_branch;
    wire [31:0] rs1_data, rs2_data;
    wire [31:0] reg_write_data;
    wire [31:0] alu_b;
    wire [31:0] imm;
    wire        reg_write, alu_src, mem_to_reg, branch, zero;
    wire [3:0]  alu_ctrl;
    assign pc_plus_4 = pc_current + 32'd4;
    assign pc_branch = pc_current + imm;
    assign pc_next   = (branch && zero) ? pc_branch : pc_plus_4;
    assign pc_out    = pc_current;
    pc pc_inst (
        .clk(clk),
        .rst(rst),
        .next_pc(pc_next),
        .pc(pc_current)
    );
    control_unit control_inst (
        .opcode(instr[6:0]),
        .funct3(instr[14:12]),
        .funct7(instr[31:25]),
        .reg_write(reg_write),
        .alu_src(alu_src),
        .mem_to_reg(mem_to_reg),
        .mem_write(mem_write),
        .mem_read(mem_read),
        .branch(branch),
        .alu_ctrl(alu_ctrl)
    );
    assign reg_write_data = mem_to_reg ? mem_data_read : alu_result;
    reg_file reg_file_inst (
        .clk(clk),
        .rst(rst),
        .reg_write(reg_write),
        .rs1_addr(instr[19:15]),
        .rs2_addr(instr[24:20]),
        .rd_addr(instr[11:7]),
        .write_data(reg_write_data),
        .rs1_data(rs1_data),
        .rs2_data(rs2_data)
    );
    imm_gen imm_gen_inst (
        .instr(instr),
        .imm(imm)
    );
    assign alu_b = alu_src ? imm : rs2_data;
    assign mem_data_write = rs2_data; 
    alu alu_inst (
        .a(rs1_data),
        .b(alu_b),
        .alu_ctrl(alu_ctrl),
        .result(alu_result),
        .zero(zero)
    );
endmodule

rtl/soc_top.v
module soc_top (
    input  wire        MAX10_CLK1_50, 
    input  wire [1:0]  KEY,          
    input  wire [9:0]  SW,            
    output wire [9:0]  LEDR,       
    output wire [6:0]  HEX0,          
    output wire [6:0]  HEX1           
);

    wire clk = MAX10_CLK1_50;
    wire rst = ~KEY[0];
    wire [31:0] pc;
    wire [31:0] instr;
    wire [31:0] mem_addr;
    wire [31:0] mem_write_data;
    wire [31:0] mem_read_data;
    wire        mem_write_en;
    wire        mem_read_en;
    reg [9:0]  reg_leds;
    reg [31:0] reg_hex;

    assign LEDR = reg_leds;
    riscv_top cpu (
        .clk(clk),
        .rst(rst),
        .pc_out(pc),
        .instr(instr),
        .alu_result(mem_addr),             
        .mem_data_write(mem_write_data),  
        .mem_data_read(mem_read_data),    
        .mem_read(mem_read_en),           
        .mem_write(mem_write_en)         
    );
    wire is_ram_addr  = (mem_addr < 32'h0000_1000);
    wire ram_write_en = mem_write_en && is_ram_addr;
    wire [31:0] ram_read_data;
    memory ram (
        .clk(clk),
        .write_en(ram_write_en),
        .addr(mem_addr),
        .write_data(mem_write_data),
        .read_data(ram_read_data)
    );
    always @(posedge clk or posedge rst) begin
        if (rst) begin
            reg_leds <= 10'b0;
            reg_hex  <= 32'b0;
        end else if (mem_write_en) begin
            if (mem_addr == 32'h8000_0000)
                reg_leds <= mem_write_data[9:0];
            else if (mem_addr == 32'h8000_0004)
                reg_hex  <= mem_write_data;
        end
    end
    assign mem_read_data = (mem_addr == 32'h8000_0008) ? {22'b0, SW} : ram_read_data;
    hex_decoder hex0_inst (.hex_digit(reg_hex[3:0]), .seg(HEX0));
    hex_decoder hex1_inst (.hex_digit(reg_hex[7:4]), .seg(HEX1));

endmodule

sim/tb_soc_top.v
`timescale 1ns / 1ps

module tb_soc_top;

    reg        MAX10_CLK1_50;
    reg  [1:0] KEY;
    reg  [9:0] SW;
    wire [9:0] LEDR;
    wire [6:0] HEX0;
    wire [6:0] HEX1;

    soc_top uut (
        .MAX10_CLK1_50(MAX10_CLK1_50),
        .KEY(KEY),
        .SW(SW),
        .LEDR(LEDR),
        .HEX0(HEX0),
        .HEX1(HEX1)
    );
    always #10 MAX10_CLK1_50 = ~MAX10_CLK1_50;

    initial begin
        $dumpfile("dump.vcd");
        $dumpvars(0, tb_soc_top);

        MAX10_CLK1_50 = 0;
        KEY = 2'b10;
        SW  = 10'b0;
        #40;
        KEY[0] = 1; 
        #5000;
        $finish;
    end

endmodule

sim/dump.vcd
$date
	Fri Oct  2 22:45:51 2026
$end
$version
	Icarus Verilog
$end
$timescale
	1ps
$end
$scope module tb_soc_top $end
$var wire 10 ! LEDR [9:0] $end
$var wire 7 " HEX1 [6:0] $end
$var wire 7 # HEX0 [6:0] $end
$var reg 2 $ KEY [1:0] $end
$var reg 1 % MAX10_CLK1_50 $end
$var reg 10 & SW [9:0] $end
$scope module uut $end
$var wire 2 ' KEY [1:0] $end
$var wire 10 ( LEDR [9:0] $end
$var wire 1 % MAX10_CLK1_50 $end
$var wire 10 ) SW [9:0] $end
$var wire 1 * clk $end
$var wire 32 + instr [31:0] $end
$var wire 1 , ram_write_en $end
$var wire 1 - rst $end
$var wire 32 . ram_read_data [31:0] $end
$var wire 32 / pc [31:0] $end
$var wire 1 0 mem_write_en $end
$var wire 32 1 mem_write_data [31:0] $end
$var wire 1 2 mem_read_en $end
$var wire 32 3 mem_read_data [31:0] $end
$var wire 32 4 mem_addr [31:0] $end
$var wire 1 5 is_ram_addr $end
$var wire 7 6 HEX1 [6:0] $end
$var wire 7 7 HEX0 [6:0] $end
$var reg 32 8 reg_hex [31:0] $end
$var reg 10 9 reg_leds [9:0] $end
$scope module cpu $end
$var wire 1 * clk $end
$var wire 32 : instr [31:0] $end
$var wire 32 ; mem_data_read [31:0] $end
$var wire 32 < mem_data_write [31:0] $end
$var wire 32 = pc_out [31:0] $end
$var wire 1 - rst $end
$var wire 1 > zero $end
$var wire 32 ? rs2_data [31:0] $end
$var wire 32 @ rs1_data [31:0] $end
$var wire 32 A reg_write_data [31:0] $end
$var wire 1 B reg_write $end
$var wire 32 C pc_plus_4 [31:0] $end
$var wire 32 D pc_next [31:0] $end
$var wire 32 E pc_current [31:0] $end
$var wire 32 F pc_branch [31:0] $end
$var wire 1 0 mem_write $end
$var wire 1 G mem_to_reg $end
$var wire 1 2 mem_read $end
$var wire 32 H imm [31:0] $end
$var wire 1 I branch $end
$var wire 1 J alu_src $end
$var wire 32 K alu_result [31:0] $end
$var wire 4 L alu_ctrl [3:0] $end
$var wire 32 M alu_b [31:0] $end
$scope module alu_inst $end
$var wire 32 N b [31:0] $end
$var wire 1 > zero $end
$var wire 4 O alu_ctrl [3:0] $end
$var wire 32 P a [31:0] $end
$var reg 32 Q result [31:0] $end
$upscope $end
$scope module control_inst $end
$var wire 3 R funct3 [2:0] $end
$var wire 8 S funct7 [7:0] $end
$var wire 7 T opcode [6:0] $end
$var reg 4 U alu_ctrl [3:0] $end
$var reg 1 J alu_src $end
$var reg 1 I branch $end
$var reg 1 2 mem_read $end
$var reg 1 G mem_to_reg $end
$var reg 1 0 mem_write $end
$var reg 1 B reg_write $end
$upscope $end
$scope module imm_gen_inst $end
$var wire 32 V instr [31:0] $end
$var reg 32 W imm [31:0] $end
$upscope $end
$scope module pc_inst $end
$var wire 1 * clk $end
$var wire 32 X next_pc [31:0] $end
$var wire 1 - rst $end
$var reg 32 Y pc [31:0] $end
$upscope $end
$scope module reg_file_inst $end
$var wire 1 * clk $end
$var wire 5 Z rd_addr [4:0] $end
$var wire 1 B reg_write $end
$var wire 5 [ rs1_addr [4:0] $end
$var wire 5 \ rs2_addr [4:0] $end
$var wire 1 - rst $end
$var wire 32 ] write_data [31:0] $end
$var wire 32 ^ rs2_data [31:0] $end
$var wire 32 _ rs1_data [31:0] $end
$var integer 32 ` i [31:0] $end
$upscope $end
$upscope $end
$scope module hex0_inst $end
$var wire 4 a hex_digit [3:0] $end
$var reg 7 b seg [6:0] $end
$upscope $end
$scope module hex1_inst $end
$var wire 4 c hex_digit [3:0] $end
$var reg 7 d seg [6:0] $end
$upscope $end
$scope module ram $end
$var wire 32 e addr [31:0] $end
$var wire 1 * clk $end
$var wire 32 f read_data [31:0] $end
$var wire 32 g write_data [31:0] $end
$var wire 1 , write_en $end
$upscope $end
$upscope $end
$upscope $end
$enddefinitions $end
$comment Show the parameter values. $end
$dumpall
$end
#0
$dumpvars
bx g
bx f
bx e
b1000000 d
b0 c
b1000000 b
b0 a
b100000 `
bx _
bx ^
bx ]
bz \
bz [
bz Z
b0 Y
b100 X
bx W
bz V
b0 U
bz T
b0zzzzzzz S
bz R
bx Q
bx P
b0 O
bx N
bx M
b0 L
bx K
0J
0I
bx H
0G
bx F
b0 E
b100 D
b100 C
0B
bx A
bx @
bx ?
x>
b0 =
bx <
bx ;
bz :
b0 9
b0 8
b1000000 7
b1000000 6
x5
bx 4
bx 3
02
bx 1
00
b0 /
bx .
1-
0,
bz +
0*
b0 )
b0 (
b10 '
b0 &
0%
b10 $
b1000000 #
b1000000 "
b0 !
$end
#10000
b100000 `
1*
1%
#20000
0*
0%
#30000
b100000 `
1*
1%
#40000
0-
0*
0%
b11 $
b11 '
#50000
b1000 D
b1000 X
b1000 C
b100 /
b100 =
b100 E
b100 Y
1*
1%
#60000
0*
0%
#70000
b1100 D
b1100 X
b1100 C
b1000 /
b1000 =
b1000 E
b1000 Y
1*
1%
#80000
0*
0%
#90000
b10000 D
b10000 X
b10000 C
b1100 /
b1100 =
b1100 E
b1100 Y
1*
1%
#100000
0*
0%
#110000
b10100 D
b10100 X
b10100 C
b10000 /
b10000 =
b10000 E
b10000 Y
1*
1%
#120000
0*
0%
#130000
b11000 D
b11000 X
b11000 C
b10100 /
b10100 =
b10100 E
b10100 Y
1*
1%
#140000
0*
0%
#150000
b11100 D
b11100 X
b11100 C
b11000 /
b11000 =
b11000 E
b11000 Y
1*
1%
#160000
0*
0%
#170000
b100000 D
b100000 X
b100000 C
b11100 /
b11100 =
b11100 E
b11100 Y
1*
1%
#180000
0*
0%
#190000
b100100 D
b100100 X
b100100 C
b100000 /
b100000 =
b100000 E
b100000 Y
1*
1%
#200000
0*
0%
#210000
b101000 D
b101000 X
b101000 C
b100100 /
b100100 =
b100100 E
b100100 Y
1*
1%
#220000
0*
0%
#230000
b101100 D
b101100 X
b101100 C
b101000 /
b101000 =
b101000 E
b101000 Y
1*
1%
#240000
0*
0%
#250000
b110000 D
b110000 X
b110000 C
b101100 /
b101100 =
b101100 E
b101100 Y
1*
1%
#260000
0*
0%
#270000
b110100 D
b110100 X
b110100 C
b110000 /
b110000 =
b110000 E
b110000 Y
1*
1%
#280000
0*
0%
#290000
b111000 D
b111000 X
b111000 C
b110100 /
b110100 =
b110100 E
b110100 Y
1*
1%
#300000
0*
0%
#310000
b111100 D
b111100 X
b111100 C
b111000 /
b111000 =
b111000 E
b111000 Y
1*
1%
#320000
0*
0%
#330000
b1000000 D
b1000000 X
b1000000 C
b111100 /
b111100 =
b111100 E
b111100 Y
1*
1%
#340000
0*
0%
#350000
b1000100 D
b1000100 X
b1000100 C
b1000000 /
b1000000 =
b1000000 E
b1000000 Y
1*
1%
#360000
0*
0%
#370000
b1001000 D
b1001000 X
b1001000 C
b1000100 /
b1000100 =
b1000100 E
b1000100 Y
1*
1%
#380000
0*
0%
#390000
b1001100 D
b1001100 X
b1001100 C
b1001000 /
b1001000 =
b1001000 E
b1001000 Y
1*
1%
#400000
0*
0%
#410000
b1010000 D
b1010000 X
b1010000 C
b1001100 /
b1001100 =
b1001100 E
b1001100 Y
1*
1%
#420000
0*
0%
#430000
b1010100 D
b1010100 X
b1010100 C
b1010000 /
b1010000 =
b1010000 E
b1010000 Y
1*
1%
#440000
0*
0%
#450000
b1011000 D
b1011000 X
b1011000 C
b1010100 /
b1010100 =
b1010100 E
b1010100 Y
1*
1%
#460000
0*
0%
#470000
b1011100 D
b1011100 X
b1011100 C
b1011000 /
b1011000 =
b1011000 E
b1011000 Y
1*
1%
#480000
0*
0%
#490000
b1100000 D
b1100000 X
b1100000 C
b1011100 /
b1011100 =
b1011100 E
b1011100 Y
1*
1%
#500000
0*
0%
#510000
b1100100 D
b1100100 X
b1100100 C
b1100000 /
b1100000 =
b1100000 E
b1100000 Y
1*
1%
#520000
0*
0%
#530000
b1101000 D
b1101000 X
b1101000 C
b1100100 /
b1100100 =
b1100100 E
b1100100 Y
1*
1%
#540000
0*
0%
#550000
b1101100 D
b1101100 X
b1101100 C
b1101000 /
b1101000 =
b1101000 E
b1101000 Y
1*
1%
#560000
0*
0%
#570000
b1110000 D
b1110000 X
b1110000 C
b1101100 /
b1101100 =
b1101100 E
b1101100 Y
1*
1%
#580000
0*
0%
#590000
b1110100 D
b1110100 X
b1110100 C
b1110000 /
b1110000 =
b1110000 E
b1110000 Y
1*
1%
#600000
0*
0%
#610000
b1111000 D
b1111000 X
b1111000 C
b1110100 /
b1110100 =
b1110100 E
b1110100 Y
1*
1%
#620000
0*
0%
#630000
b1111100 D
b1111100 X
b1111100 C
b1111000 /
b1111000 =
b1111000 E
b1111000 Y
1*
1%
#640000
0*
0%
#650000
b10000000 D
b10000000 X
b10000000 C
b1111100 /
b1111100 =
b1111100 E
b1111100 Y
1*
1%
#660000
0*
0%
#670000
b10000100 D
b10000100 X
b10000100 C
b10000000 /
b10000000 =
b10000000 E
b10000000 Y
1*
1%
#680000
0*
0%
#690000
b10001000 D
b10001000 X
b10001000 C
b10000100 /
b10000100 =
b10000100 E
b10000100 Y
1*
1%
#700000
0*
0%
#710000
b10001100 D
b10001100 X
b10001100 C
b10001000 /
b10001000 =
b10001000 E
b10001000 Y
1*
1%
#720000
0*
0%
#730000
b10010000 D
b10010000 X
b10010000 C
b10001100 /
b10001100 =
b10001100 E
b10001100 Y
1*
1%
#740000
0*
0%
#750000
b10010100 D
b10010100 X
b10010100 C
b10010000 /
b10010000 =
b10010000 E
b10010000 Y
1*
1%
#760000
0*
0%
#770000
b10011000 D
b10011000 X
b10011000 C
b10010100 /
b10010100 =
b10010100 E
b10010100 Y
1*
1%
#780000
0*
0%
#790000
b10011100 D
b10011100 X
b10011100 C
b10011000 /
b10011000 =
b10011000 E
b10011000 Y
1*
1%
#800000
0*
0%
#810000
b10100000 D
b10100000 X
b10100000 C
b10011100 /
b10011100 =
b10011100 E
b10011100 Y
1*
1%
#820000
0*
0%
#830000
b10100100 D
b10100100 X
b10100100 C
b10100000 /
b10100000 =
b10100000 E
b10100000 Y
1*
1%
#840000
0*
0%
#850000
b10101000 D
b10101000 X
b10101000 C
b10100100 /
b10100100 =
b10100100 E
b10100100 Y
1*
1%
#860000
0*
0%
#870000
b10101100 D
b10101100 X
b10101100 C
b10101000 /
b10101000 =
b10101000 E
b10101000 Y
1*
1%
#880000
0*
0%
#890000
b10110000 D
b10110000 X
b10110000 C
b10101100 /
b10101100 =
b10101100 E
b10101100 Y
1*
1%
#900000
0*
0%
#910000
b10110100 D
b10110100 X
b10110100 C
b10110000 /
b10110000 =
b10110000 E
b10110000 Y
1*
1%
#920000
0*
0%
#930000
b10111000 D
b10111000 X
b10111000 C
b10110100 /
b10110100 =
b10110100 E
b10110100 Y
1*
1%
#940000
0*
0%
#950000
b10111100 D
b10111100 X
b10111100 C
b10111000 /
b10111000 =
b10111000 E
b10111000 Y
1*
1%
#960000
0*
0%
#970000
b11000000 D
b11000000 X
b11000000 C
b10111100 /
b10111100 =
b10111100 E
b10111100 Y
1*
1%
#980000
0*
0%
#990000
b11000100 D
b11000100 X
b11000100 C
b11000000 /
b11000000 =
b11000000 E
b11000000 Y
1*
1%
#1000000
0*
0%
#1010000
b11001000 D
b11001000 X
b11001000 C
b11000100 /
b11000100 =
b11000100 E
b11000100 Y
1*
1%
#1020000
0*
0%
#1030000
b11001100 D
b11001100 X
b11001100 C
b11001000 /
b11001000 =
b11001000 E
b11001000 Y
1*
1%
#1040000
0*
0%
#1050000
b11010000 D
b11010000 X
b11010000 C
b11001100 /
b11001100 =
b11001100 E
b11001100 Y
1*
1%
#1060000
0*
0%
#1070000
b11010100 D
b11010100 X
b11010100 C
b11010000 /
b11010000 =
b11010000 E
b11010000 Y
1*
1%
#1080000
0*
0%
#1090000
b11011000 D
b11011000 X
b11011000 C
b11010100 /
b11010100 =
b11010100 E
b11010100 Y
1*
1%
#1100000
0*
0%
#1110000
b11011100 D
b11011100 X
b11011100 C
b11011000 /
b11011000 =
b11011000 E
b11011000 Y
1*
1%
#1120000
0*
0%
#1130000
b11100000 D
b11100000 X
b11100000 C
b11011100 /
b11011100 =
b11011100 E
b11011100 Y
1*
1%
#1140000
0*
0%
#1150000
b11100100 D
b11100100 X
b11100100 C
b11100000 /
b11100000 =
b11100000 E
b11100000 Y
1*
1%
#1160000
0*
0%
#1170000
b11101000 D
b11101000 X
b11101000 C
b11100100 /
b11100100 =
b11100100 E
b11100100 Y
1*
1%
#1180000
0*
0%
#1190000
b11101100 D
b11101100 X
b11101100 C
b11101000 /
b11101000 =
b11101000 E
b11101000 Y
1*
1%
#1200000
0*
0%
#1210000
b11110000 D
b11110000 X
b11110000 C
b11101100 /
b11101100 =
b11101100 E
b11101100 Y
1*
1%
#1220000
0*
0%
#1230000
b11110100 D
b11110100 X
b11110100 C
b11110000 /
b11110000 =
b11110000 E
b11110000 Y
1*
1%
#1240000
0*
0%
#1250000
b11111000 D
b11111000 X
b11111000 C
b11110100 /
b11110100 =
b11110100 E
b11110100 Y
1*
1%
#1260000
0*
0%
#1270000
b11111100 D
b11111100 X
b11111100 C
b11111000 /
b11111000 =
b11111000 E
b11111000 Y
1*
1%
#1280000
0*
0%
#1290000
b100000000 D
b100000000 X
b100000000 C
b11111100 /
b11111100 =
b11111100 E
b11111100 Y
1*
1%
#1300000
0*
0%
#1310000
b100000100 D
b100000100 X
b100000100 C
b100000000 /
b100000000 =
b100000000 E
b100000000 Y
1*
1%
#1320000
0*
0%
#1330000
b100001000 D
b100001000 X
b100001000 C
b100000100 /
b100000100 =
b100000100 E
b100000100 Y
1*
1%
#1340000
0*
0%
#1350000
b100001100 D
b100001100 X
b100001100 C
b100001000 /
b100001000 =
b100001000 E
b100001000 Y
1*
1%
#1360000
0*
0%
#1370000
b100010000 D
b100010000 X
b100010000 C
b100001100 /
b100001100 =
b100001100 E
b100001100 Y
1*
1%
#1380000
0*
0%
#1390000
b100010100 D
b100010100 X
b100010100 C
b100010000 /
b100010000 =
b100010000 E
b100010000 Y
1*
1%
#1400000
0*
0%
#1410000
b100011000 D
b100011000 X
b100011000 C
b100010100 /
b100010100 =
b100010100 E
b100010100 Y
1*
1%
#1420000
0*
0%
#1430000
b100011100 D
b100011100 X
b100011100 C
b100011000 /
b100011000 =
b100011000 E
b100011000 Y
1*
1%
#1440000
0*
0%
#1450000
b100100000 D
b100100000 X
b100100000 C
b100011100 /
b100011100 =
b100011100 E
b100011100 Y
1*
1%
#1460000
0*
0%
#1470000
b100100100 D
b100100100 X
b100100100 C
b100100000 /
b100100000 =
b100100000 E
b100100000 Y
1*
1%
#1480000
0*
0%
#1490000
b100101000 D
b100101000 X
b100101000 C
b100100100 /
b100100100 =
b100100100 E
b100100100 Y
1*
1%
#1500000
0*
0%
#1510000
b100101100 D
b100101100 X
b100101100 C
b100101000 /
b100101000 =
b100101000 E
b100101000 Y
1*
1%
#1520000
0*
0%
#1530000
b100110000 D
b100110000 X
b100110000 C
b100101100 /
b100101100 =
b100101100 E
b100101100 Y
1*
1%
#1540000
0*
0%
#1550000
b100110100 D
b100110100 X
b100110100 C
b100110000 /
b100110000 =
b100110000 E
b100110000 Y
1*
1%
#1560000
0*
0%
#1570000
b100111000 D
b100111000 X
b100111000 C
b100110100 /
b100110100 =
b100110100 E
b100110100 Y
1*
1%
#1580000
0*
0%
#1590000
b100111100 D
b100111100 X
b100111100 C
b100111000 /
b100111000 =
b100111000 E
b100111000 Y
1*
1%
#1600000
0*
0%
#1610000
b101000000 D
b101000000 X
b101000000 C
b100111100 /
b100111100 =
b100111100 E
b100111100 Y
1*
1%
#1620000
0*
0%
#1630000
b101000100 D
b101000100 X
b101000100 C
b101000000 /
b101000000 =
b101000000 E
b101000000 Y
1*
1%
#1640000
0*
0%
#1650000
b101001000 D
b101001000 X
b101001000 C
b101000100 /
b101000100 =
b101000100 E
b101000100 Y
1*
1%
#1660000
0*
0%
#1670000
b101001100 D
b101001100 X
b101001100 C
b101001000 /
b101001000 =
b101001000 E
b101001000 Y
1*
1%
#1680000
0*
0%
#1690000
b101010000 D
b101010000 X
b101010000 C
b101001100 /
b101001100 =
b101001100 E
b101001100 Y
1*
1%
#1700000
0*
0%
#1710000
b101010100 D
b101010100 X
b101010100 C
b101010000 /
b101010000 =
b101010000 E
b101010000 Y
1*
1%
#1720000
0*
0%
#1730000
b101011000 D
b101011000 X
b101011000 C
b101010100 /
b101010100 =
b101010100 E
b101010100 Y
1*
1%
#1740000
0*
0%
#1750000
b101011100 D
b101011100 X
b101011100 C
b101011000 /
b101011000 =
b101011000 E
b101011000 Y
1*
1%
#1760000
0*
0%
#1770000
b101100000 D
b101100000 X
b101100000 C
b101011100 /
b101011100 =
b101011100 E
b101011100 Y
1*
1%
#1780000
0*
0%
#1790000
b101100100 D
b101100100 X
b101100100 C
b101100000 /
b101100000 =
b101100000 E
b101100000 Y
1*
1%
#1800000
0*
0%
#1810000
b101101000 D
b101101000 X
b101101000 C
b101100100 /
b101100100 =
b101100100 E
b101100100 Y
1*
1%
#1820000
0*
0%
#1830000
b101101100 D
b101101100 X
b101101100 C
b101101000 /
b101101000 =
b101101000 E
b101101000 Y
1*
1%
#1840000
0*
0%
#1850000
b101110000 D
b101110000 X
b101110000 C
b101101100 /
b101101100 =
b101101100 E
b101101100 Y
1*
1%
#1860000
0*
0%
#1870000
b101110100 D
b101110100 X
b101110100 C
b101110000 /
b101110000 =
b101110000 E
b101110000 Y
1*
1%
#1880000
0*
0%
#1890000
b101111000 D
b101111000 X
b101111000 C
b101110100 /
b101110100 =
b101110100 E
b101110100 Y
1*
1%
#1900000
0*
0%
#1910000
b101111100 D
b101111100 X
b101111100 C
b101111000 /
b101111000 =
b101111000 E
b101111000 Y
1*
1%
#1920000
0*
0%
#1930000
b110000000 D
b110000000 X
b110000000 C
b101111100 /
b101111100 =
b101111100 E
b101111100 Y
1*
1%
#1940000
0*
0%
#1950000
b110000100 D
b110000100 X
b110000100 C
b110000000 /
b110000000 =
b110000000 E
b110000000 Y
1*
1%
#1960000
0*
0%
#1970000
b110001000 D
b110001000 X
b110001000 C
b110000100 /
b110000100 =
b110000100 E
b110000100 Y
1*
1%
#1980000
0*
0%
#1990000
b110001100 D
b110001100 X
b110001100 C
b110001000 /
b110001000 =
b110001000 E
b110001000 Y
1*
1%
#2000000
0*
0%
#2010000
b110010000 D
b110010000 X
b110010000 C
b110001100 /
b110001100 =
b110001100 E
b110001100 Y
1*
1%
#2020000
0*
0%
#2030000
b110010100 D
b110010100 X
b110010100 C
b110010000 /
b110010000 =
b110010000 E
b110010000 Y
1*
1%
#2040000
0*
0%
#2050000
b110011000 D
b110011000 X
b110011000 C
b110010100 /
b110010100 =
b110010100 E
b110010100 Y
1*
1%
#2060000
0*
0%
#2070000
b110011100 D
b110011100 X
b110011100 C
b110011000 /
b110011000 =
b110011000 E
b110011000 Y
1*
1%
#2080000
0*
0%
#2090000
b110100000 D
b110100000 X
b110100000 C
b110011100 /
b110011100 =
b110011100 E
b110011100 Y
1*
1%
#2100000
0*
0%
#2110000
b110100100 D
b110100100 X
b110100100 C
b110100000 /
b110100000 =
b110100000 E
b110100000 Y
1*
1%
#2120000
0*
0%
#2130000
b110101000 D
b110101000 X
b110101000 C
b110100100 /
b110100100 =
b110100100 E
b110100100 Y
1*
1%
#2140000
0*
0%
#2150000
b110101100 D
b110101100 X
b110101100 C
b110101000 /
b110101000 =
b110101000 E
b110101000 Y
1*
1%
#2160000
0*
0%
#2170000
b110110000 D
b110110000 X
b110110000 C
b110101100 /
b110101100 =
b110101100 E
b110101100 Y
1*
1%
#2180000
0*
0%
#2190000
b110110100 D
b110110100 X
b110110100 C
b110110000 /
b110110000 =
b110110000 E
b110110000 Y
1*
1%
#2200000
0*
0%
#2210000
b110111000 D
b110111000 X
b110111000 C
b110110100 /
b110110100 =
b110110100 E
b110110100 Y
1*
1%
#2220000
0*
0%
